topsis_nandini_102303129/__init__.py
topsis_nandini_102303129/topsis.py
topsis_nandini_102303129-1.0.0.dist-info/licenses/LICENSE
topsis_nandini_102303129-1.0.0.dist-info/METADATA
topsis_nandini_102303129-1.0.0.dist-info/WHEEL
topsis_nandini_102303129-1.0.0.dist-info/entry_points.txt
topsis_nandini_102303129-1.0.0.dist-info/top_level.txt
topsis_nandini_102303129-1.0.0.dist-info/RECORD
